aeecde/__init__.py
aeecde/test.py
aeecde/algorithms/DE.py
aeecde/algorithms/__init__.py
aeecde/algorithms/algodev.py
aeecde/architectures/__init__.py
aeecde/architectures/individual.py
aeecde/architectures/population.py
aeecde/operators/DE.py
aeecde/operators/__init__.py
aeecde/problems/__init__.py
aeecde/problems/bbobbenchmarks.py
aeecde/problems/problem.py
aeecde/publics/__init__.py
aeecde/publics/parameterize.py
aeecde/publics/tools.py
aeecde/tuners/__init__.py
aeecde/tuners/tuner.py
aeecde-1.0.1.dist-info/LICENSE
aeecde-1.0.1.dist-info/METADATA
aeecde-1.0.1.dist-info/WHEEL
aeecde-1.0.1.dist-info/top_level.txt
aeecde-1.0.1.dist-info/RECORD
